brunch/__init__.py
brunch/brunch.s.HTML
brunch/drive info.s.HTML
brunch/notices.s.HTML
brunch/tutorial.s.HTML
brunch/__agenda/agenda.s.HTML
brunch/_license/license.s.HTML
brunch/_status/status.proc.py
brunch/_status/status.s.HTML
brunch/_status/status/status_1.py
brunch/_status/status/status_2_start_scan_and_sculpt.py
brunch/_status/status/status_3_end_of_drive_scans.py
brunch/_status/status/status_4_end_scan_and_sculpt.py
brunch/_status/status/status_5_status_scan.py
brunch/_status/status/status_6_after_end_of_drive_sculpt.py
brunch/_status/status/erase/status_1.py
brunch/_status/status_advanced/advanced_status_1_entire_drive.py
brunch/_status/status_advanced/advanced_status_2_entire_drive_erase.py
brunch/_status/status_shell/s1/flask_server.py
brunch/_status/status_shell/s1/status_1.py
brunch/clique/__init__.py
brunch/clique/_status/status_1.py
brunch/decor/__init__.py
brunch/erase/__init__.py
brunch/erase/clique.py
brunch/modules/LS_BLK/__init__.py
brunch/modules/LS_BLK/calc_size.py
brunch/modules/repair/repair.s.HTML
brunch/scan/__init__.py
brunch/scan/can_scan.py
brunch/scan/clique.py
brunch/scan/is_last_byte.py
brunch/scan/scan.s.HTML
brunch/scan/similar techs.s.HTML
brunch/sculpt/__init__.py
brunch/sculpt/clique.py
brunch/sculpt/sculpt.s.HTML
brunch/sculpt/strategies/patterns.s.HTML
brunch/sculpt/strategies/strategy_1.py
brunch/sculpt/strategies/strategy_2.py
brunch-1.0.0.data/scripts/brunch
brunch-1.0.0.dist-info/METADATA
brunch-1.0.0.dist-info/WHEEL
brunch-1.0.0.dist-info/top_level.txt
brunch-1.0.0.dist-info/RECORD
