Metadata-Version: 2.1
Name: brunch
Version: 1.0.0
License: CL
Requires-Dist: OHF
Requires-Dist: shares
Requires-Dist: ships
Requires-Dist: flask
Requires-Dist: jsonschema
Requires-Dist: rich
